mapnik/__init__.py
mapnik/mapnik_settings.py
mapnik/printing.py
mapnik/paths.py
mapnik/_mapnik.so
mapnik/libmapnik.so.3.0
mapnik/plugins/input/csv.input
mapnik/plugins/input/gdal.input
mapnik/plugins/input/geojson.input
mapnik/plugins/input/hello.input
mapnik/plugins/input/ogr.input
mapnik/plugins/input/osm.input
mapnik/plugins/input/pgraster.input
mapnik/plugins/input/postgis.input
mapnik/plugins/input/raster.input
mapnik/plugins/input/shape.input
mapnik/plugins/input/sqlite.input
mapnik/plugins/input/topojson.input
mapnik/plugins/fonts/DejaVuSans-Bold.ttf
mapnik/plugins/fonts/DejaVuSans-BoldOblique.ttf
mapnik/plugins/fonts/DejaVuSans-ExtraLight.ttf
mapnik/plugins/fonts/DejaVuSans-Oblique.ttf
mapnik/plugins/fonts/DejaVuSans.ttf
mapnik/plugins/fonts/DejaVuSansCondensed-Bold.ttf
mapnik/plugins/fonts/DejaVuSansCondensed-BoldOblique.ttf
mapnik/plugins/fonts/DejaVuSansCondensed-Oblique.ttf
mapnik/plugins/fonts/DejaVuSansCondensed.ttf
mapnik/plugins/fonts/DejaVuSansMono-Bold.ttf
mapnik/plugins/fonts/DejaVuSansMono-Oblique.ttf
mapnik/plugins/fonts/DejaVuSansMono-BoldOblique.ttf
mapnik/plugins/fonts/DejaVuSansMono.ttf
mapnik/plugins/fonts/DejaVuSerif-Bold.ttf
mapnik/plugins/fonts/DejaVuSerif-BoldItalic.ttf
mapnik/plugins/fonts/DejaVuSerif-Italic.ttf
mapnik/plugins/fonts/DejaVuSerif.ttf
mapnik/plugins/fonts/DejaVuSerifCondensed-Bold.ttf
mapnik/plugins/fonts/DejaVuSerifCondensed-BoldItalic.ttf
mapnik/plugins/fonts/DejaVuSerifCondensed-Italic.ttf
mapnik/plugins/fonts/DejaVuSerifCondensed.ttf
mapnik/plugins/fonts/unifont-7.0.05.ttf
mapnik/plugins/icu/icudt54l.dat
mapnik/plugins/gdal/nitf_spec.xsd
mapnik/plugins/gdal/ogrvrt.xsd
mapnik/plugins/gdal/osmconf.ini
mapnik/plugins/gdal/ozi_datum.csv
mapnik/plugins/gdal/ozi_ellips.csv
mapnik/plugins/gdal/pci_datum.txt
mapnik/plugins/gdal/pci_ellips.txt
mapnik/plugins/gdal/pcs.csv
mapnik/plugins/gdal/pcs.override.csv
mapnik/plugins/gdal/prime_meridian.csv
mapnik-0.1.dist-info/top_level.txt
mapnik-0.1.dist-info/METADATA
mapnik-0.1.dist-info/DESCRIPTION.rst
mapnik-0.1.dist-info/metadata.json
mapnik-0.1.dist-info/WHEEL
mapnik-0.1.dist-info/RECORD
