Metadata-Version: 2.0
Name: mapnik
Version: 0.1
Summary: Python bindings for Mapnik
Home-page: http://mapnik.org/
Author: Blake Thompson
Author-email: flippmoke@gmail.com
License: GNU LESSER GENERAL PUBLIC LICENSE
Keywords: mapnik mapbox mapping carteography
Platform: UNKNOWN
